Metadata-Version: 2.1
Name: metacatalog-search
Version: 0.5.1
Summary: Full-Text Search extenstion for Metacatalog
Home-page: UNKNOWN
Author: Mirko Mälicke
Author-email: mirko.maelicke@kit.edu
License: GPL v3
Platform: UNKNOWN
